tests/wigner.py
wigners-0.3.1.dist-info/RECORD
wigners-0.3.1.dist-info/WHEEL
wigners-0.3.1.dist-info/top_level.txt
wigners-0.3.1.dist-info/METADATA
wigners-0.3.1.dist-info/licenses/LICENSE-APACHE
wigners-0.3.1.dist-info/licenses/LICENSE-MIT
wigners/_wigners.so
wigners/__init__.py
