Metadata-Version: 2.4
Name: wigners
Version: 0.3.1
Summary: Compute Wigner 3j and Clebsch-Gordan coefficients
Author-email: Guillaume Fraux <guillaume.fraux@epfl.ch>
License-Expression: Apache-2.0 OR MIT
Project-URL: homepage, https://github.com/Luthaf/wigners
Project-URL: repository, https://github.com/Luthaf/wigners
Keywords: clebsch-gordan,wigner
Classifier: Development Status :: 4 - Beta
Classifier: Environment :: Console
Classifier: Topic :: Scientific/Engineering
Classifier: Topic :: Scientific/Engineering :: Chemistry
Classifier: Topic :: Scientific/Engineering :: Physics
Requires-Python: >=3.9
License-File: LICENSE-APACHE
License-File: LICENSE-MIT
Requires-Dist: numpy
Dynamic: license-file
